[
  {
    "title": "315名单",
    "category": "暂无",
    "url": "https://m.weibo.cn/search?containerid=100103type%3D1%26t%3D10%26q%3D315%E5%90%8D%E5%8D%95&stream_entry_id=31&isnewpage=1&extparam=seat%3D1%26q%3D315%25E5%2590%258D%25E5%258D%2595%26dgr%3D0%26filter_type%3Drealtimehot%26c_type%3D31%26realpos%3D1%26band_rank%3D1%26cate%3D5001%26flag%3D16%26stream_entry_id%3D31%26lcate%3D5001%26pos%3D0%26display_time%3D1742094369%26pre_seqid%3D17420943694530328354923",
    "hot": 2811755,
    "ads": false,
    "readCount": 280000000,
    "discussCount": 71000,
    "origin": 23000
  },
  {
    "title": "老公去世短视频最后为了卖洗发水",
    "category": "社会",
    "description": "你见过这种卖惨视频吗？",
    "url": "https://m.weibo.cn/search?containerid=100103type%3D1%26t%3D10%26q%3D%23%E8%80%81%E5%85%AC%E5%8E%BB%E4%B8%96%E7%9F%AD%E8%A7%86%E9%A2%91%E6%9C%80%E5%90%8E%E4%B8%BA%E4%BA%86%E5%8D%96%E6%B4%97%E5%8F%91%E6%B0%B4%23&stream_entry_id=31&isnewpage=1&extparam=seat%3D1%26q%3D%2523%25E8%2580%2581%25E5%2585%25AC%25E5%258E%25BB%25E4%25B8%2596%25E7%259F%25AD%25E8%25A7%2586%25E9%25A2%2591%25E6%259C%2580%25E5%2590%258E%25E4%25B8%25BA%25E4%25BA%2586%25E5%258D%2596%25E6%25B4%2597%25E5%258F%2591%25E6%25B0%25B4%2523%26dgr%3D0%26filter_type%3Drealtimehot%26c_type%3D31%26realpos%3D2%26band_rank%3D2%26cate%3D5001%26flag%3D1%26stream_entry_id%3D31%26lcate%3D5001%26pos%3D1%26display_time%3D1742094369%26pre_seqid%3D17420943694530328354923",
    "hot": 1719026,
    "ads": false,
    "readCount": 21580000,
    "discussCount": 1761,
    "origin": 428
  },
  {
    "title": "烟雨漓江将中国水墨画具象化了",
    "category": "社会",
    "description": "近日，广西桂林再现烟雨漓江美景。轻纱般的薄雾笼罩在碧绿的江面上，为这幅天然的山水水墨画添上一抹神秘的色彩。游客畅游其中，宛如置身一幅流动的中国山水画卷。",
    "url": "https://m.weibo.cn/search?containerid=100103type%3D1%26t%3D10%26q%3D%23%E7%83%9F%E9%9B%A8%E6%BC%93%E6%B1%9F%E5%B0%86%E4%B8%AD%E5%9B%BD%E6%B0%B4%E5%A2%A8%E7%94%BB%E5%85%B7%E8%B1%A1%E5%8C%96%E4%BA%86%23&stream_entry_id=31&isnewpage=1&extparam=seat%3D1%26q%3D%2523%25E7%2583%259F%25E9%259B%25A8%25E6%25BC%2593%25E6%25B1%259F%25E5%25B0%2586%25E4%25B8%25AD%25E5%259B%25BD%25E6%25B0%25B4%25E5%25A2%25A8%25E7%2594%25BB%25E5%2585%25B7%25E8%25B1%25A1%25E5%258C%2596%25E4%25BA%2586%2523%26dgr%3D0%26filter_type%3Drealtimehot%26c_type%3D31%26realpos%3D3%26band_rank%3D3%26cate%3D5001%26flag%3D0%26stream_entry_id%3D31%26lcate%3D5001%26pos%3D2%26display_time%3D1742094369%26pre_seqid%3D17420943694530328354923",
    "hot": 1293106,
    "ads": false,
    "readCount": 22840000,
    "discussCount": 6980,
    "origin": 705
  },
  {
    "title": "韩安冉因整容过度鼻子呼吸不畅",
    "category": "明星",
    "url": "https://m.weibo.cn/search?containerid=100103type%3D1%26t%3D10%26q%3D%23%E9%9F%A9%E5%AE%89%E5%86%89%E5%9B%A0%E6%95%B4%E5%AE%B9%E8%BF%87%E5%BA%A6%E9%BC%BB%E5%AD%90%E5%91%BC%E5%90%B8%E4%B8%8D%E7%95%85%23&stream_entry_id=31&isnewpage=1&extparam=seat%3D1%26q%3D%2523%25E9%259F%25A9%25E5%25AE%2589%25E5%2586%2589%25E5%259B%25A0%25E6%2595%25B4%25E5%25AE%25B9%25E8%25BF%2587%25E5%25BA%25A6%25E9%25BC%25BB%25E5%25AD%2590%25E5%2591%25BC%25E5%2590%25B8%25E4%25B8%258D%25E7%2595%2585%2523%26dgr%3D0%26filter_type%3Drealtimehot%26c_type%3D31%26realpos%3D4%26band_rank%3D4%26cate%3D5001%26flag%3D1%26stream_entry_id%3D31%26lcate%3D5001%26pos%3D3%26display_time%3D1742094369%26pre_seqid%3D17420943694530328354923",
    "hot": 1227087,
    "ads": false,
    "readCount": 50251000,
    "discussCount": 5001,
    "origin": 1701
  },
  {
    "title": "央视起底黑公关",
    "category": "社会",
    "description": "机器人水军评论，付费发稿，造谣抹黑，这些恶意营销方式被业内人士统称为“黑公关”。",
    "url": "https://m.weibo.cn/search?containerid=100103type%3D1%26t%3D10%26q%3D%23%E5%A4%AE%E8%A7%86%E8%B5%B7%E5%BA%95%E9%BB%91%E5%85%AC%E5%85%B3%23&stream_entry_id=31&isnewpage=1&extparam=seat%3D1%26q%3D%2523%25E5%25A4%25AE%25E8%25A7%2586%25E8%25B5%25B7%25E5%25BA%2595%25E9%25BB%2591%25E5%2585%25AC%25E5%2585%25B3%2523%26dgr%3D0%26filter_type%3Drealtimehot%26c_type%3D31%26realpos%3D5%26band_rank%3D5%26cate%3D5001%26flag%3D1%26stream_entry_id%3D31%26lcate%3D5001%26pos%3D4%26display_time%3D1742094369%26pre_seqid%3D17420943694530328354923",
    "hot": 1146164,
    "ads": false,
    "readCount": 17615000,
    "discussCount": 4340,
    "origin": 958
  },
  {
    "title": "苏菲发声明",
    "category": "社会",
    "url": "https://m.weibo.cn/search?containerid=100103type%3D1%26t%3D10%26q%3D%23%E8%8B%8F%E8%8F%B2%E5%8F%91%E5%A3%B0%E6%98%8E%23&stream_entry_id=31&isnewpage=1&extparam=seat%3D1%26q%3D%2523%25E8%258B%258F%25E8%258F%25B2%25E5%258F%2591%25E5%25A3%25B0%25E6%2598%258E%2523%26dgr%3D0%26filter_type%3Drealtimehot%26c_type%3D31%26realpos%3D6%26band_rank%3D6%26cate%3D5001%26flag%3D0%26stream_entry_id%3D31%26lcate%3D5001%26pos%3D5%26display_time%3D1742094369%26pre_seqid%3D17420943694530328354923",
    "hot": 991628,
    "ads": false,
    "readCount": 100000000,
    "discussCount": 9235,
    "origin": 2695
  },
  {
    "title": "啄木鸟称放弃公关",
    "category": "财经",
    "description": "3月15日深夜，@啄木鸟家庭维修 发布第二次声明",
    "url": "https://m.weibo.cn/search?containerid=100103type%3D1%26t%3D10%26q%3D%23%E5%95%84%E6%9C%A8%E9%B8%9F%E7%A7%B0%E6%94%BE%E5%BC%83%E5%85%AC%E5%85%B3%23&stream_entry_id=31&isnewpage=1&extparam=seat%3D1%26q%3D%2523%25E5%2595%2584%25E6%259C%25A8%25E9%25B8%259F%25E7%25A7%25B0%25E6%2594%25BE%25E5%25BC%2583%25E5%2585%25AC%25E5%2585%25B3%2523%26dgr%3D0%26filter_type%3Drealtimehot%26c_type%3D31%26realpos%3D7%26band_rank%3D7%26cate%3D5001%26flag%3D2%26stream_entry_id%3D31%26lcate%3D5001%26pos%3D6%26display_time%3D1742094369%26pre_seqid%3D17420943694530328354923",
    "hot": 837492,
    "ads": false,
    "readCount": 110000000,
    "discussCount": 14000,
    "origin": 2269
  },
  {
    "title": "郭晓婷购买的贴身衣物有霉斑",
    "category": "明星-内地",
    "description": "在旅行和出差时曾多次使用这类产品，但竟然在其中发现了疑似霉斑或污渍的异物！ ​",
    "url": "https://m.weibo.cn/search?containerid=100103type%3D1%26t%3D10%26q%3D%23%E9%83%AD%E6%99%93%E5%A9%B7%E8%B4%AD%E4%B9%B0%E7%9A%84%E8%B4%B4%E8%BA%AB%E8%A1%A3%E7%89%A9%E6%9C%89%E9%9C%89%E6%96%91%23&stream_entry_id=31&isnewpage=1&extparam=seat%3D1%26q%3D%2523%25E9%2583%25AD%25E6%2599%2593%25E5%25A9%25B7%25E8%25B4%25AD%25E4%25B9%25B0%25E7%259A%2584%25E8%25B4%25B4%25E8%25BA%25AB%25E8%25A1%25A3%25E7%2589%25A9%25E6%259C%2589%25E9%259C%2589%25E6%2596%2591%2523%26dgr%3D0%26filter_type%3Drealtimehot%26c_type%3D31%26realpos%3D8%26band_rank%3D8%26cate%3D5001%26flag%3D2%26stream_entry_id%3D31%26lcate%3D5001%26pos%3D7%26display_time%3D1742094369%26pre_seqid%3D17420943694530328354923",
    "hot": 833994,
    "ads": false,
    "readCount": 67302000,
    "discussCount": 4960,
    "origin": 1529
  },
  {
    "title": "保水虾仁涉事企业被查",
    "category": "社会",
    "description": "央视3·15晚会曝光“保水虾仁”问题后，湛江市市场监管局迅速联合湛江市公安局组成工作专班，会同属地市场监管、公安部门，联合组织执法人员赶赴涉事企业开展检查。",
    "url": "https://m.weibo.cn/search?containerid=100103type%3D1%26t%3D10%26q%3D%23%E4%BF%9D%E6%B0%B4%E8%99%BE%E4%BB%81%E6%B6%89%E4%BA%8B%E4%BC%81%E4%B8%9A%E8%A2%AB%E6%9F%A5%23&stream_entry_id=31&isnewpage=1&extparam=seat%3D1%26q%3D%2523%25E4%25BF%259D%25E6%25B0%25B4%25E8%2599%25BE%25E4%25BB%2581%25E6%25B6%2589%25E4%25BA%258B%25E4%25BC%2581%25E4%25B8%259A%25E8%25A2%25AB%25E6%259F%25A5%2523%26dgr%3D0%26filter_type%3Drealtimehot%26c_type%3D31%26realpos%3D9%26band_rank%3D9%26cate%3D5001%26flag%3D1%26stream_entry_id%3D31%26lcate%3D5001%26pos%3D8%26display_time%3D1742094369%26pre_seqid%3D17420943694530328354923",
    "hot": 832765,
    "ads": false,
    "readCount": 2344000,
    "discussCount": 257,
    "origin": 56
  },
  {
    "title": "好的一次性内裤有两个标准",
    "category": "社会",
    "description": "一次性内裤到底是如何生产的？有哪些卫生标准？作为普通消费者，如何才能避免选不卫生的一次性内裤呢？",
    "url": "https://m.weibo.cn/search?containerid=100103type%3D1%26t%3D10%26q%3D%23%E5%A5%BD%E7%9A%84%E4%B8%80%E6%AC%A1%E6%80%A7%E5%86%85%E8%A3%A4%E6%9C%89%E4%B8%A4%E4%B8%AA%E6%A0%87%E5%87%86%23&stream_entry_id=31&isnewpage=1&extparam=seat%3D1%26q%3D%2523%25E5%25A5%25BD%25E7%259A%2584%25E4%25B8%2580%25E6%25AC%25A1%25E6%2580%25A7%25E5%2586%2585%25E8%25A3%25A4%25E6%259C%2589%25E4%25B8%25A4%25E4%25B8%25AA%25E6%25A0%2587%25E5%2587%2586%2523%26dgr%3D0%26filter_type%3Drealtimehot%26c_type%3D31%26realpos%3D10%26band_rank%3D10%26cate%3D5001%26flag%3D1%26stream_entry_id%3D31%26lcate%3D5001%26pos%3D9%26display_time%3D1742094369%26pre_seqid%3D17420943694530328354923",
    "hot": 832580,
    "ads": false,
    "readCount": 6169000,
    "discussCount": 897,
    "origin": 110
  },
  {
    "title": "金秀贤金赛纶恋爱次日画面",
    "category": "明星",
    "url": "https://m.weibo.cn/search?containerid=100103type%3D1%26t%3D10%26q%3D%23%E9%87%91%E7%A7%80%E8%B4%A4%E9%87%91%E8%B5%9B%E7%BA%B6%E6%81%8B%E7%88%B1%E6%AC%A1%E6%97%A5%E7%94%BB%E9%9D%A2%23&stream_entry_id=31&isnewpage=1&extparam=seat%3D1%26q%3D%2523%25E9%2587%2591%25E7%25A7%2580%25E8%25B4%25A4%25E9%2587%2591%25E8%25B5%259B%25E7%25BA%25B6%25E6%2581%258B%25E7%2588%25B1%25E6%25AC%25A1%25E6%2597%25A5%25E7%2594%25BB%25E9%259D%25A2%2523%26dgr%3D0%26filter_type%3Drealtimehot%26c_type%3D31%26realpos%3D11%26band_rank%3D11%26cate%3D5001%26flag%3D1%26stream_entry_id%3D31%26lcate%3D5001%26pos%3D10%26display_time%3D1742094369%26pre_seqid%3D17420943694530328354923",
    "hot": 832502,
    "ads": false,
    "readCount": 8349000,
    "discussCount": 305,
    "origin": 114
  },
  {
    "title": "315晚会",
    "category": "财经",
    "description": "中央广播电视总台“3·15”晚会准备就绪，3月15日20点在央视财经频道现场直播。央视财经新媒体、央视频、央广经济之声、央视网将同步播出。",
    "url": "https://m.weibo.cn/search?containerid=100103type%3D1%26t%3D10%26q%3D%23315%E6%99%9A%E4%BC%9A%23&stream_entry_id=31&isnewpage=1&extparam=seat%3D1%26q%3D%2523315%25E6%2599%259A%25E4%25BC%259A%2523%26dgr%3D0%26filter_type%3Drealtimehot%26c_type%3D31%26realpos%3D12%26band_rank%3D12%26cate%3D5001%26flag%3D0%26stream_entry_id%3D31%26lcate%3D5001%26pos%3D11%26display_time%3D1742094369%26pre_seqid%3D17420943694530328354923",
    "hot": 791077,
    "ads": false,
    "readCount": 9640000000,
    "discussCount": 2647000,
    "origin": 191000
  },
  {
    "title": "翻新卫生巾",
    "category": "社会",
    "url": "https://m.weibo.cn/search?containerid=100103type%3D1%26t%3D10%26q%3D%23%E7%BF%BB%E6%96%B0%E5%8D%AB%E7%94%9F%E5%B7%BE%23&stream_entry_id=31&isnewpage=1&extparam=seat%3D1%26q%3D%2523%25E7%25BF%25BB%25E6%2596%25B0%25E5%258D%25AB%25E7%2594%259F%25E5%25B7%25BE%2523%26dgr%3D0%26filter_type%3Drealtimehot%26c_type%3D31%26realpos%3D13%26band_rank%3D13%26cate%3D5001%26flag%3D0%26stream_entry_id%3D31%26lcate%3D5001%26pos%3D12%26display_time%3D1742094369%26pre_seqid%3D17420943694530328354923",
    "hot": 756052,
    "ads": false,
    "readCount": 480000000,
    "discussCount": 227000,
    "origin": 73000
  },
  {
    "title": "孙颖莎vs王艺迪",
    "category": "体育",
    "description": "2025WTT重庆冠军赛，孙颖莎vs王艺迪。",
    "url": "https://m.weibo.cn/search?containerid=100103type%3D1%26t%3D10%26q%3D%23%E5%AD%99%E9%A2%96%E8%8E%8Evs%E7%8E%8B%E8%89%BA%E8%BF%AA%23&stream_entry_id=31&isnewpage=1&extparam=seat%3D1%26q%3D%2523%25E5%25AD%2599%25E9%25A2%2596%25E8%258E%258Evs%25E7%258E%258B%25E8%2589%25BA%25E8%25BF%25AA%2523%26dgr%3D0%26filter_type%3Drealtimehot%26c_type%3D31%26realpos%3D14%26band_rank%3D14%26cate%3D5001%26flag%3D1%26stream_entry_id%3D31%26lcate%3D5001%26pos%3D13%26display_time%3D1742094369%26pre_seqid%3D17420943694530328354923",
    "hot": 627885,
    "ads": false,
    "readCount": 580000000,
    "discussCount": 174000,
    "origin": 24000
  },
  {
    "title": "警方通报复旦一学生失联后死亡",
    "category": "社会",
    "url": "https://m.weibo.cn/search?containerid=100103type%3D1%26t%3D10%26q%3D%23%E8%AD%A6%E6%96%B9%E9%80%9A%E6%8A%A5%E5%A4%8D%E6%97%A6%E4%B8%80%E5%AD%A6%E7%94%9F%E5%A4%B1%E8%81%94%E5%90%8E%E6%AD%BB%E4%BA%A1%23&stream_entry_id=31&isnewpage=1&extparam=seat%3D1%26q%3D%2523%25E8%25AD%25A6%25E6%2596%25B9%25E9%2580%259A%25E6%258A%25A5%25E5%25A4%258D%25E6%2597%25A6%25E4%25B8%2580%25E5%25AD%25A6%25E7%2594%259F%25E5%25A4%25B1%25E8%2581%2594%25E5%2590%258E%25E6%25AD%25BB%25E4%25BA%25A1%2523%26dgr%3D0%26filter_type%3Drealtimehot%26c_type%3D31%26realpos%3D15%26band_rank%3D15%26cate%3D5001%26flag%3D1%26stream_entry_id%3D31%26lcate%3D5001%26pos%3D14%26display_time%3D1742094369%26pre_seqid%3D17420943694530328354923",
    "hot": 618633,
    "ads": false,
    "readCount": 7382000,
    "discussCount": 503,
    "origin": 119
  },
  {
    "title": "薛仁雅为取关金秀贤清空所有关注",
    "category": "明星",
    "description": "薛仁雅为取关金秀贤清空所有关注",
    "url": "https://m.weibo.cn/search?containerid=100103type%3D1%26t%3D10%26q%3D%23%E8%96%9B%E4%BB%81%E9%9B%85%E4%B8%BA%E5%8F%96%E5%85%B3%E9%87%91%E7%A7%80%E8%B4%A4%E6%B8%85%E7%A9%BA%E6%89%80%E6%9C%89%E5%85%B3%E6%B3%A8%23&stream_entry_id=31&isnewpage=1&extparam=seat%3D1%26q%3D%2523%25E8%2596%259B%25E4%25BB%2581%25E9%259B%2585%25E4%25B8%25BA%25E5%258F%2596%25E5%2585%25B3%25E9%2587%2591%25E7%25A7%2580%25E8%25B4%25A4%25E6%25B8%2585%25E7%25A9%25BA%25E6%2589%2580%25E6%259C%2589%25E5%2585%25B3%25E6%25B3%25A8%2523%26dgr%3D0%26filter_type%3Drealtimehot%26c_type%3D31%26realpos%3D16%26band_rank%3D16%26cate%3D5001%26flag%3D1%26stream_entry_id%3D31%26lcate%3D5001%26pos%3D15%26display_time%3D1742094369%26pre_seqid%3D17420943694530328354923",
    "hot": 617479,
    "ads": false,
    "readCount": 15501000,
    "discussCount": 663,
    "origin": 294
  },
  {
    "title": "自由点道歉",
    "category": "财经",
    "description": "道歉了！ ​​​",
    "url": "https://m.weibo.cn/search?containerid=100103type%3D1%26t%3D10%26q%3D%23%E8%87%AA%E7%94%B1%E7%82%B9%E9%81%93%E6%AD%89%23&stream_entry_id=31&isnewpage=1&extparam=seat%3D1%26q%3D%2523%25E8%2587%25AA%25E7%2594%25B1%25E7%2582%25B9%25E9%2581%2593%25E6%25AD%2589%2523%26dgr%3D0%26filter_type%3Drealtimehot%26c_type%3D31%26realpos%3D17%26band_rank%3D17%26cate%3D5001%26flag%3D0%26stream_entry_id%3D31%26lcate%3D5001%26pos%3D16%26display_time%3D1742094369%26pre_seqid%3D17420943694530328354923",
    "hot": 614434,
    "ads": false,
    "readCount": 120000000,
    "discussCount": 18000,
    "origin": 6749
  },
  {
    "title": "韩安冉妈妈喊话前女婿泽西还钱",
    "category": "明星",
    "description": "韩安冉妈妈喊话前女婿泽西还钱",
    "url": "https://m.weibo.cn/search?containerid=100103type%3D1%26t%3D10%26q%3D%23%E9%9F%A9%E5%AE%89%E5%86%89%E5%A6%88%E5%A6%88%E5%96%8A%E8%AF%9D%E5%89%8D%E5%A5%B3%E5%A9%BF%E6%B3%BD%E8%A5%BF%E8%BF%98%E9%92%B1%23&stream_entry_id=31&isnewpage=1&extparam=seat%3D1%26q%3D%2523%25E9%259F%25A9%25E5%25AE%2589%25E5%2586%2589%25E5%25A6%2588%25E5%25A6%2588%25E5%2596%258A%25E8%25AF%259D%25E5%2589%258D%25E5%25A5%25B3%25E5%25A9%25BF%25E6%25B3%25BD%25E8%25A5%25BF%25E8%25BF%2598%25E9%2592%25B1%2523%26dgr%3D0%26filter_type%3Drealtimehot%26c_type%3D31%26realpos%3D18%26band_rank%3D18%26cate%3D5001%26flag%3D1%26stream_entry_id%3D31%26lcate%3D5001%26pos%3D17%26display_time%3D1742094369%26pre_seqid%3D17420943694530328354923",
    "hot": 544814,
    "ads": false,
    "readCount": 13581000,
    "discussCount": 757,
    "origin": 96
  },
  {
    "title": "李惠利朴彩英合照",
    "category": "明星-日韩",
    "description": "李惠利朴彩英合照",
    "url": "https://m.weibo.cn/search?containerid=100103type%3D1%26t%3D10%26q%3D%23%E6%9D%8E%E6%83%A0%E5%88%A9%E6%9C%B4%E5%BD%A9%E8%8B%B1%E5%90%88%E7%85%A7%23&stream_entry_id=31&isnewpage=1&extparam=seat%3D1%26q%3D%2523%25E6%259D%258E%25E6%2583%25A0%25E5%2588%25A9%25E6%259C%25B4%25E5%25BD%25A9%25E8%258B%25B1%25E5%2590%2588%25E7%2585%25A7%2523%26dgr%3D0%26filter_type%3Drealtimehot%26c_type%3D31%26realpos%3D19%26band_rank%3D19%26cate%3D5001%26flag%3D1%26stream_entry_id%3D31%26lcate%3D5001%26pos%3D18%26display_time%3D1742094369%26pre_seqid%3D17420943694530328354923",
    "hot": 540882,
    "ads": false,
    "readCount": 8402000,
    "discussCount": 496,
    "origin": 196
  },
  {
    "title": "刘耀文还是戴墨镜吧",
    "category": "明星",
    "description": "太阳太刺眼了，浪费了三张自拍，害我少看了这几张呜呜呜 ​",
    "url": "https://m.weibo.cn/search?containerid=100103type%3D1%26t%3D10%26q%3D%23%E5%88%98%E8%80%80%E6%96%87%E8%BF%98%E6%98%AF%E6%88%B4%E5%A2%A8%E9%95%9C%E5%90%A7%23&stream_entry_id=31&isnewpage=1&extparam=seat%3D1%26q%3D%2523%25E5%2588%2598%25E8%2580%2580%25E6%2596%2587%25E8%25BF%2598%25E6%2598%25AF%25E6%2588%25B4%25E5%25A2%25A8%25E9%2595%259C%25E5%2590%25A7%2523%26dgr%3D0%26filter_type%3Drealtimehot%26c_type%3D31%26realpos%3D20%26band_rank%3D20%26cate%3D5001%26flag%3D0%26stream_entry_id%3D31%26lcate%3D5001%26pos%3D19%26display_time%3D1742094369%26pre_seqid%3D17420943694530328354923",
    "hot": 540236,
    "ads": false,
    "readCount": 15959000,
    "discussCount": 15000,
    "origin": 1304
  },
  {
    "title": "金赛纶 体面",
    "category": "暂无",
    "url": "https://m.weibo.cn/search?containerid=100103type%3D1%26t%3D10%26q%3D%E9%87%91%E8%B5%9B%E7%BA%B6+%E4%BD%93%E9%9D%A2&stream_entry_id=31&isnewpage=1&extparam=seat%3D1%26q%3D%25E9%2587%2591%25E8%25B5%259B%25E7%25BA%25B6%2520%25E4%25BD%2593%25E9%259D%25A2%26dgr%3D0%26filter_type%3Drealtimehot%26c_type%3D31%26realpos%3D21%26band_rank%3D21%26cate%3D5001%26flag%3D2%26stream_entry_id%3D31%26lcate%3D5001%26pos%3D20%26display_time%3D1742094369%26pre_seqid%3D17420943694530328354923",
    "hot": 540076,
    "ads": false,
    "readCount": 23349000,
    "discussCount": 3345,
    "origin": 1039
  },
  {
    "title": "一次性内裤爆雷",
    "category": "财经",
    "description": "一次性内裤凭借方便、卫生，成为市场热销的产品。但火爆热销的背后，事实真的如此吗？",
    "url": "https://m.weibo.cn/search?containerid=100103type%3D1%26t%3D10%26q%3D%23%E4%B8%80%E6%AC%A1%E6%80%A7%E5%86%85%E8%A3%A4%E7%88%86%E9%9B%B7%23&stream_entry_id=31&isnewpage=1&extparam=seat%3D1%26q%3D%2523%25E4%25B8%2580%25E6%25AC%25A1%25E6%2580%25A7%25E5%2586%2585%25E8%25A3%25A4%25E7%2588%2586%25E9%259B%25B7%2523%26dgr%3D0%26filter_type%3Drealtimehot%26c_type%3D31%26realpos%3D22%26band_rank%3D22%26cate%3D5001%26flag%3D0%26stream_entry_id%3D31%26lcate%3D5001%26pos%3D21%26display_time%3D1742094369%26pre_seqid%3D17420943694530328354923",
    "hot": 527753,
    "ads": false,
    "readCount": 270000000,
    "discussCount": 81000,
    "origin": 21000
  },
  {
    "title": "女子篡改室友考公岗位被拘",
    "category": "社会",
    "description": "3月15日，安徽黄山市2025年度考试录用公务员笔试开考，而考生汪女士因此前大学室友程某的举动，差点无法顺利参考。",
    "url": "https://m.weibo.cn/search?containerid=100103type%3D1%26t%3D10%26q%3D%23%E5%A5%B3%E5%AD%90%E7%AF%A1%E6%94%B9%E5%AE%A4%E5%8F%8B%E8%80%83%E5%85%AC%E5%B2%97%E4%BD%8D%E8%A2%AB%E6%8B%98%23&stream_entry_id=31&isnewpage=1&extparam=seat%3D1%26q%3D%2523%25E5%25A5%25B3%25E5%25AD%2590%25E7%25AF%25A1%25E6%2594%25B9%25E5%25AE%25A4%25E5%258F%258B%25E8%2580%2583%25E5%2585%25AC%25E5%25B2%2597%25E4%25BD%258D%25E8%25A2%25AB%25E6%258B%2598%2523%26dgr%3D0%26filter_type%3Drealtimehot%26c_type%3D31%26realpos%3D23%26band_rank%3D23%26cate%3D5001%26flag%3D0%26stream_entry_id%3D31%26lcate%3D5001%26pos%3D22%26display_time%3D1742094369%26pre_seqid%3D17420943694530328354923",
    "hot": 523550,
    "ads": false,
    "readCount": 38090000,
    "discussCount": 3585,
    "origin": 722
  },
  {
    "title": "网友在雷军评论区刷屏小米做卫生巾",
    "category": "社会",
    "description": "3月15日，央视财经3·15晚会曝光劣质卫生巾和纸尿裤，且数量巨大。众多网友纷纷跑到@雷军 评论区刷屏，希望小米能生产卫生巾和纸尿裤等产品。",
    "url": "https://m.weibo.cn/search?containerid=100103type%3D1%26t%3D10%26q%3D%23%E7%BD%91%E5%8F%8B%E5%9C%A8%E9%9B%B7%E5%86%9B%E8%AF%84%E8%AE%BA%E5%8C%BA%E5%88%B7%E5%B1%8F%E5%B0%8F%E7%B1%B3%E5%81%9A%E5%8D%AB%E7%94%9F%E5%B7%BE%23&stream_entry_id=31&isnewpage=1&extparam=seat%3D1%26q%3D%2523%25E7%25BD%2591%25E5%258F%258B%25E5%259C%25A8%25E9%259B%25B7%25E5%2586%259B%25E8%25AF%2584%25E8%25AE%25BA%25E5%258C%25BA%25E5%2588%25B7%25E5%25B1%258F%25E5%25B0%258F%25E7%25B1%25B3%25E5%2581%259A%25E5%258D%25AB%25E7%2594%259F%25E5%25B7%25BE%2523%26dgr%3D0%26filter_type%3Drealtimehot%26c_type%3D31%26realpos%3D24%26band_rank%3D24%26cate%3D5001%26flag%3D1%26stream_entry_id%3D31%26lcate%3D5001%26pos%3D23%26display_time%3D1742094369%26pre_seqid%3D17420943694530328354923",
    "hot": 508866,
    "ads": false,
    "readCount": 10495000,
    "discussCount": 1363,
    "origin": 314
  },
  {
    "title": "全棉时代回应",
    "category": "暂无",
    "url": "https://m.weibo.cn/search?containerid=100103type%3D1%26t%3D10%26q%3D%23%E5%85%A8%E6%A3%89%E6%97%B6%E4%BB%A3%E5%9B%9E%E5%BA%94%23&stream_entry_id=31&isnewpage=1&extparam=seat%3D1%26q%3D%2523%25E5%2585%25A8%25E6%25A3%2589%25E6%2597%25B6%25E4%25BB%25A3%25E5%259B%259E%25E5%25BA%2594%2523%26dgr%3D0%26filter_type%3Drealtimehot%26c_type%3D31%26realpos%3D25%26band_rank%3D25%26cate%3D5001%26flag%3D0%26stream_entry_id%3D31%26lcate%3D5001%26pos%3D24%26display_time%3D1742094369%26pre_seqid%3D17420943694530328354923",
    "hot": 406234,
    "ads": false,
    "readCount": 100000000,
    "discussCount": 12000,
    "origin": 1482
  },
  {
    "title": "蜜雪冰城",
    "category": "美食",
    "description": "你爱我，我爱你~ 蜜雪冰城甜蜜蜜",
    "url": "https://m.weibo.cn/search?containerid=100103type%3D1%26t%3D10%26q%3D%E8%9C%9C%E9%9B%AA%E5%86%B0%E5%9F%8E&stream_entry_id=31&isnewpage=1&extparam=seat%3D1%26q%3D%25E8%259C%259C%25E9%259B%25AA%25E5%2586%25B0%25E5%259F%258E%26dgr%3D0%26filter_type%3Drealtimehot%26c_type%3D31%26realpos%3D26%26band_rank%3D26%26cate%3D5001%26flag%3D0%26stream_entry_id%3D31%26lcate%3D5001%26pos%3D25%26display_time%3D1742094369%26pre_seqid%3D17420943694530328354923",
    "hot": 375920,
    "ads": false,
    "readCount": 450000000,
    "discussCount": 755000,
    "origin": 64000
  },
  {
    "title": "九田家烤肉被曝光门店店长称很惭愧",
    "category": "社会",
    "description": "3月14日晚，湖北经视“3·15特别报道”曝光了九田家黑牛烤肉料理门店员工没有健康证、员工餐桌徒手甩制金针菇肉卷等问题。3月15日，九田家黑牛烤肉咸宁万达广场店店长表示，将“回炉再造”，再次培训学习。",
    "url": "https://m.weibo.cn/search?containerid=100103type%3D1%26t%3D10%26q%3D%23%E4%B9%9D%E7%94%B0%E5%AE%B6%E7%83%A4%E8%82%89%E8%A2%AB%E6%9B%9D%E5%85%89%E9%97%A8%E5%BA%97%E5%BA%97%E9%95%BF%E7%A7%B0%E5%BE%88%E6%83%AD%E6%84%A7%23&stream_entry_id=31&isnewpage=1&extparam=seat%3D1%26q%3D%2523%25E4%25B9%259D%25E7%2594%25B0%25E5%25AE%25B6%25E7%2583%25A4%25E8%2582%2589%25E8%25A2%25AB%25E6%259B%259D%25E5%2585%2589%25E9%2597%25A8%25E5%25BA%2597%25E5%25BA%2597%25E9%2595%25BF%25E7%25A7%25B0%25E5%25BE%2588%25E6%2583%25AD%25E6%2584%25A7%2523%26dgr%3D0%26filter_type%3Drealtimehot%26c_type%3D31%26realpos%3D27%26band_rank%3D27%26cate%3D5001%26flag%3D0%26stream_entry_id%3D31%26lcate%3D5001%26pos%3D26%26display_time%3D1742094369%26pre_seqid%3D17420943694530328354923",
    "hot": 249102,
    "ads": false,
    "readCount": 28552000,
    "discussCount": 1387,
    "origin": 343
  },
  {
    "title": "睡眠负债的人身体有9个表现",
    "category": "科普",
    "description": "“睡眠负债”是指睡眠不足导致疲劳无法消除而残留了下来，并像借债一样逐渐累积。即使过完周末，很多人却仍旧感到疲惫：浑身乏力、大脑迟钝、犯困打盹、做什么都提不起精神……此外，平时出现以下几种表现，其实是身体释放的“缺觉信号”↓",
    "url": "https://m.weibo.cn/search?containerid=100103type%3D1%26t%3D10%26q%3D%23%E7%9D%A1%E7%9C%A0%E8%B4%9F%E5%80%BA%E7%9A%84%E4%BA%BA%E8%BA%AB%E4%BD%93%E6%9C%899%E4%B8%AA%E8%A1%A8%E7%8E%B0%23&stream_entry_id=31&isnewpage=1&extparam=seat%3D1%26q%3D%2523%25E7%259D%25A1%25E7%259C%25A0%25E8%25B4%259F%25E5%2580%25BA%25E7%259A%2584%25E4%25BA%25BA%25E8%25BA%25AB%25E4%25BD%2593%25E6%259C%25899%25E4%25B8%25AA%25E8%25A1%25A8%25E7%258E%25B0%2523%26dgr%3D0%26filter_type%3Drealtimehot%26c_type%3D31%26realpos%3D28%26band_rank%3D28%26cate%3D5001%26flag%3D1%26stream_entry_id%3D31%26lcate%3D5001%26pos%3D27%26display_time%3D1742094369%26pre_seqid%3D17420943694530328354923",
    "hot": 235152,
    "ads": false,
    "readCount": 6276000,
    "discussCount": 835,
    "origin": 113
  },
  {
    "title": "杨洋把杨迪泼溺水了",
    "category": "明星-内地",
    "url": "https://m.weibo.cn/search?containerid=100103type%3D1%26t%3D10%26q%3D%23%E6%9D%A8%E6%B4%8B%E6%8A%8A%E6%9D%A8%E8%BF%AA%E6%B3%BC%E6%BA%BA%E6%B0%B4%E4%BA%86%23&stream_entry_id=31&isnewpage=1&extparam=seat%3D1%26q%3D%2523%25E6%259D%25A8%25E6%25B4%258B%25E6%258A%258A%25E6%259D%25A8%25E8%25BF%25AA%25E6%25B3%25BC%25E6%25BA%25BA%25E6%25B0%25B4%25E4%25BA%2586%2523%26dgr%3D0%26filter_type%3Drealtimehot%26c_type%3D31%26realpos%3D29%26band_rank%3D29%26cate%3D5001%26flag%3D1%26stream_entry_id%3D31%26lcate%3D5001%26pos%3D28%26display_time%3D1742094369%26pre_seqid%3D17420943694530328354923",
    "hot": 227939,
    "ads": false,
    "readCount": 3914000,
    "discussCount": 411,
    "origin": 121
  },
  {
    "title": "韦雪说前夫忘不掉她",
    "category": "明星",
    "url": "https://m.weibo.cn/search?containerid=100103type%3D1%26t%3D10%26q%3D%23%E9%9F%A6%E9%9B%AA%E8%AF%B4%E5%89%8D%E5%A4%AB%E5%BF%98%E4%B8%8D%E6%8E%89%E5%A5%B9%23&stream_entry_id=31&isnewpage=1&extparam=seat%3D1%26q%3D%2523%25E9%259F%25A6%25E9%259B%25AA%25E8%25AF%25B4%25E5%2589%258D%25E5%25A4%25AB%25E5%25BF%2598%25E4%25B8%258D%25E6%258E%2589%25E5%25A5%25B9%2523%26dgr%3D0%26filter_type%3Drealtimehot%26c_type%3D31%26realpos%3D30%26band_rank%3D30%26cate%3D5001%26flag%3D1%26stream_entry_id%3D31%26lcate%3D5001%26pos%3D29%26display_time%3D1742094369%26pre_seqid%3D17420943694530328354923",
    "hot": 224884,
    "ads": false,
    "readCount": 10397000,
    "discussCount": 1019,
    "origin": 63
  },
  {
    "title": "自由点报案",
    "category": "财经",
    "description": "月15日，@自由点Freemore 发布品牌官方声明",
    "url": "https://m.weibo.cn/search?containerid=100103type%3D1%26t%3D10%26q%3D%23%E8%87%AA%E7%94%B1%E7%82%B9%E6%8A%A5%E6%A1%88%23&stream_entry_id=31&isnewpage=1&extparam=seat%3D1%26q%3D%2523%25E8%2587%25AA%25E7%2594%25B1%25E7%2582%25B9%25E6%258A%25A5%25E6%25A1%2588%2523%26dgr%3D0%26filter_type%3Drealtimehot%26c_type%3D31%26realpos%3D31%26band_rank%3D31%26cate%3D5001%26flag%3D0%26stream_entry_id%3D31%26lcate%3D5001%26pos%3D30%26display_time%3D1742094369%26pre_seqid%3D17420943694530328354923",
    "hot": 223467,
    "ads": false,
    "readCount": 64286000,
    "discussCount": 3639,
    "origin": 1225
  },
  {
    "title": "女校",
    "category": "校园",
    "url": "https://m.weibo.cn/search?containerid=100103type%3D1%26t%3D10%26q%3D%E5%A5%B3%E6%A0%A1&stream_entry_id=31&isnewpage=1&extparam=seat%3D1%26q%3D%25E5%25A5%25B3%25E6%25A0%25A1%26dgr%3D0%26filter_type%3Drealtimehot%26c_type%3D31%26realpos%3D32%26band_rank%3D32%26cate%3D5001%26flag%3D1%26stream_entry_id%3D31%26lcate%3D5001%26pos%3D31%26display_time%3D1742094369%26pre_seqid%3D17420943694530328354923",
    "hot": 219720,
    "ads": false,
    "readCount": 36241000,
    "discussCount": 96000,
    "origin": 4209
  },
  {
    "title": "班味好重的订婚宴",
    "category": "暂无",
    "url": "https://m.weibo.cn/search?containerid=100103type%3D1%26t%3D10%26q%3D%E7%8F%AD%E5%91%B3%E5%A5%BD%E9%87%8D%E7%9A%84%E8%AE%A2%E5%A9%9A%E5%AE%B4&stream_entry_id=31&isnewpage=1&extparam=seat%3D1%26q%3D%25E7%258F%25AD%25E5%2591%25B3%25E5%25A5%25BD%25E9%2587%258D%25E7%259A%2584%25E8%25AE%25A2%25E5%25A9%259A%25E5%25AE%25B4%26dgr%3D0%26filter_type%3Drealtimehot%26c_type%3D31%26realpos%3D33%26band_rank%3D33%26cate%3D5001%26flag%3D1%26stream_entry_id%3D31%26lcate%3D5001%26pos%3D32%26display_time%3D1742094369%26pre_seqid%3D17420943694530328354923",
    "hot": 215970,
    "ads": false,
    "readCount": 461000,
    "discussCount": 27,
    "origin": 22
  },
  {
    "title": "护舒宝声明",
    "category": "社会",
    "description": "​​​3月15日，@护舒宝 回应315晚会曝光翻新卫生巾。",
    "url": "https://m.weibo.cn/search?containerid=100103type%3D1%26t%3D10%26q%3D%23%E6%8A%A4%E8%88%92%E5%AE%9D%E5%A3%B0%E6%98%8E%23&stream_entry_id=31&isnewpage=1&extparam=seat%3D1%26q%3D%2523%25E6%258A%25A4%25E8%2588%2592%25E5%25AE%259D%25E5%25A3%25B0%25E6%2598%258E%2523%26dgr%3D0%26filter_type%3Drealtimehot%26c_type%3D31%26realpos%3D34%26band_rank%3D34%26cate%3D5001%26flag%3D0%26stream_entry_id%3D31%26lcate%3D5001%26pos%3D33%26display_time%3D1742094369%26pre_seqid%3D17420943694530328354923",
    "hot": 202105,
    "ads": false,
    "readCount": 85246000,
    "discussCount": 8297,
    "origin": 2579
  },
  {
    "title": "美国24小时40多起龙卷风",
    "category": "社会",
    "description": "当地时间15日，据美国广播公司报道，过去24小时内，40多起龙卷风席卷了美国8个州。",
    "url": "https://m.weibo.cn/search?containerid=100103type%3D1%26t%3D10%26q%3D%23%E7%BE%8E%E5%9B%BD24%E5%B0%8F%E6%97%B640%E5%A4%9A%E8%B5%B7%E9%BE%99%E5%8D%B7%E9%A3%8E%23&stream_entry_id=31&isnewpage=1&extparam=seat%3D1%26q%3D%2523%25E7%25BE%258E%25E5%259B%25BD24%25E5%25B0%258F%25E6%2597%25B640%25E5%25A4%259A%25E8%25B5%25B7%25E9%25BE%2599%25E5%258D%25B7%25E9%25A3%258E%2523%26dgr%3D0%26filter_type%3Drealtimehot%26c_type%3D31%26realpos%3D35%26band_rank%3D35%26cate%3D5001%26flag%3D1%26stream_entry_id%3D31%26lcate%3D5001%26pos%3D34%26display_time%3D1742094369%26pre_seqid%3D17420943694530328354923",
    "hot": 201340,
    "ads": false,
    "readCount": 870000,
    "discussCount": 250,
    "origin": 21
  },
  {
    "title": "王力宏说是南昌拉了我一把",
    "category": "明星",
    "description": "3月15日，江西南昌，王力宏在首场巡演现场回忆，2023年12月10日南昌的一场拼盘演唱会是他复工后的首次公开演出，南昌观众的热情接纳和鼓励让他感受到“英雄城”的温暖。这场演出成为他走出低谷、重启音乐事业的关键节点，他激动地表示“南昌是第一座城市告诉我‘二哥，你可以来这边唱歌’。",
    "url": "https://m.weibo.cn/search?containerid=100103type%3D1%26t%3D10%26q%3D%23%E7%8E%8B%E5%8A%9B%E5%AE%8F%E8%AF%B4%E6%98%AF%E5%8D%97%E6%98%8C%E6%8B%89%E4%BA%86%E6%88%91%E4%B8%80%E6%8A%8A%23&stream_entry_id=31&isnewpage=1&extparam=seat%3D1%26q%3D%2523%25E7%258E%258B%25E5%258A%259B%25E5%25AE%258F%25E8%25AF%25B4%25E6%2598%25AF%25E5%258D%2597%25E6%2598%258C%25E6%258B%2589%25E4%25BA%2586%25E6%2588%2591%25E4%25B8%2580%25E6%258A%258A%2523%26dgr%3D0%26filter_type%3Drealtimehot%26c_type%3D31%26realpos%3D36%26band_rank%3D36%26cate%3D5001%26flag%3D0%26stream_entry_id%3D31%26lcate%3D5001%26pos%3D35%26display_time%3D1742094369%26pre_seqid%3D17420943694530328354923",
    "hot": 200962,
    "ads": false,
    "readCount": 43290000,
    "discussCount": 2231,
    "origin": 465
  },
  {
    "title": "薛凯琪演唱会泣不成声",
    "category": "明星-港台",
    "description": "薛凯琪泣不成声……",
    "url": "https://m.weibo.cn/search?containerid=100103type%3D1%26t%3D10%26q%3D%23%E8%96%9B%E5%87%AF%E7%90%AA%E6%BC%94%E5%94%B1%E4%BC%9A%E6%B3%A3%E4%B8%8D%E6%88%90%E5%A3%B0%23&stream_entry_id=31&isnewpage=1&extparam=seat%3D1%26q%3D%2523%25E8%2596%259B%25E5%2587%25AF%25E7%2590%25AA%25E6%25BC%2594%25E5%2594%25B1%25E4%25BC%259A%25E6%25B3%25A3%25E4%25B8%258D%25E6%2588%2590%25E5%25A3%25B0%2523%26dgr%3D0%26filter_type%3Drealtimehot%26c_type%3D31%26realpos%3D37%26band_rank%3D37%26cate%3D5001%26flag%3D0%26stream_entry_id%3D31%26lcate%3D5001%26pos%3D36%26display_time%3D1742094369%26pre_seqid%3D17420943694530328354923",
    "hot": 200917,
    "ads": false,
    "readCount": 78932000,
    "discussCount": 12000,
    "origin": 1813
  },
  {
    "title": "全棉时代 奈丝公主",
    "category": "暂无",
    "url": "https://m.weibo.cn/search?containerid=100103type%3D1%26t%3D10%26q%3D%E5%85%A8%E6%A3%89%E6%97%B6%E4%BB%A3+%E5%A5%88%E4%B8%9D%E5%85%AC%E4%B8%BB&stream_entry_id=31&isnewpage=1&extparam=seat%3D1%26q%3D%25E5%2585%25A8%25E6%25A3%2589%25E6%2597%25B6%25E4%25BB%25A3%2520%25E5%25A5%2588%25E4%25B8%259D%25E5%2585%25AC%25E4%25B8%25BB%26dgr%3D0%26filter_type%3Drealtimehot%26c_type%3D31%26realpos%3D38%26band_rank%3D38%26cate%3D5001%26flag%3D0%26stream_entry_id%3D31%26lcate%3D5001%26pos%3D37%26display_time%3D1742094369%26pre_seqid%3D17420943694530328354923",
    "hot": 198390,
    "ads": false,
    "readCount": 5728000,
    "discussCount": 1182,
    "origin": 384
  },
  {
    "title": "80余执法人员进驻啄木鸟公司",
    "category": "社会",
    "description": "重庆市市场监督管理局发布通报，出动执法人员80余人，进驻重庆啄木鸟网络科技有限公司总部及其分子公司。",
    "url": "https://m.weibo.cn/search?containerid=100103type%3D1%26t%3D10%26q%3D%2380%E4%BD%99%E6%89%A7%E6%B3%95%E4%BA%BA%E5%91%98%E8%BF%9B%E9%A9%BB%E5%95%84%E6%9C%A8%E9%B8%9F%E5%85%AC%E5%8F%B8%23&stream_entry_id=31&isnewpage=1&extparam=seat%3D1%26q%3D%252380%25E4%25BD%2599%25E6%2589%25A7%25E6%25B3%2595%25E4%25BA%25BA%25E5%2591%2598%25E8%25BF%259B%25E9%25A9%25BB%25E5%2595%2584%25E6%259C%25A8%25E9%25B8%259F%25E5%2585%25AC%25E5%258F%25B8%2523%26dgr%3D0%26filter_type%3Drealtimehot%26c_type%3D31%26realpos%3D39%26band_rank%3D39%26cate%3D5001%26flag%3D0%26stream_entry_id%3D31%26lcate%3D5001%26pos%3D38%26display_time%3D1742094369%26pre_seqid%3D17420943694530328354923",
    "hot": 193114,
    "ads": false,
    "readCount": 18549000,
    "discussCount": 3498,
    "origin": 481
  },
  {
    "title": "椰子水",
    "category": "暂无",
    "url": "https://m.weibo.cn/search?containerid=100103type%3D1%26t%3D10%26q%3D%E6%A4%B0%E5%AD%90%E6%B0%B4&stream_entry_id=31&isnewpage=1&extparam=seat%3D1%26q%3D%25E6%25A4%25B0%25E5%25AD%2590%25E6%25B0%25B4%26dgr%3D0%26filter_type%3Drealtimehot%26c_type%3D31%26realpos%3D40%26band_rank%3D40%26cate%3D5001%26flag%3D0%26stream_entry_id%3D31%26lcate%3D5001%26pos%3D39%26display_time%3D1742094369%26pre_seqid%3D17420943694530328354923",
    "hot": 190905,
    "ads": false,
    "readCount": 37225000,
    "discussCount": 49000,
    "origin": 6337
  },
  {
    "title": "全棉时代",
    "category": "其他",
    "url": "https://m.weibo.cn/search?containerid=100103type%3D1%26t%3D10%26q%3D%E5%85%A8%E6%A3%89%E6%97%B6%E4%BB%A3&stream_entry_id=31&isnewpage=1&extparam=seat%3D1%26q%3D%25E5%2585%25A8%25E6%25A3%2589%25E6%2597%25B6%25E4%25BB%25A3%26dgr%3D0%26filter_type%3Drealtimehot%26c_type%3D31%26realpos%3D41%26band_rank%3D41%26cate%3D5001%26flag%3D0%26stream_entry_id%3D31%26lcate%3D5001%26pos%3D40%26display_time%3D1742094369%26pre_seqid%3D17420943694530328354923",
    "hot": 190796,
    "ads": false,
    "readCount": 440000000,
    "discussCount": 1983000,
    "origin": 30000
  },
  {
    "title": "看315晚会天塌了",
    "category": "暂无",
    "url": "https://m.weibo.cn/search?containerid=100103type%3D1%26t%3D10%26q%3D%E7%9C%8B315%E6%99%9A%E4%BC%9A%E5%A4%A9%E5%A1%8C%E4%BA%86&stream_entry_id=31&isnewpage=1&extparam=seat%3D1%26q%3D%25E7%259C%258B315%25E6%2599%259A%25E4%25BC%259A%25E5%25A4%25A9%25E5%25A1%258C%25E4%25BA%2586%26dgr%3D0%26filter_type%3Drealtimehot%26c_type%3D31%26realpos%3D42%26band_rank%3D42%26cate%3D5001%26flag%3D0%26stream_entry_id%3D31%26lcate%3D5001%26pos%3D41%26display_time%3D1742094369%26pre_seqid%3D17420943694530328354923",
    "hot": 184178,
    "ads": false,
    "readCount": 25985000,
    "discussCount": 7679,
    "origin": 2034
  },
  {
    "title": "315当晚9省市连夜执法",
    "category": "社会",
    "url": "https://m.weibo.cn/search?containerid=100103type%3D1%26t%3D10%26q%3D%23315%E5%BD%93%E6%99%9A9%E7%9C%81%E5%B8%82%E8%BF%9E%E5%A4%9C%E6%89%A7%E6%B3%95%23&stream_entry_id=31&isnewpage=1&extparam=seat%3D1%26q%3D%2523315%25E5%25BD%2593%25E6%2599%259A9%25E7%259C%2581%25E5%25B8%2582%25E8%25BF%259E%25E5%25A4%259C%25E6%2589%25A7%25E6%25B3%2595%2523%26dgr%3D0%26filter_type%3Drealtimehot%26c_type%3D31%26realpos%3D43%26band_rank%3D43%26cate%3D5001%26flag%3D1%26stream_entry_id%3D31%26lcate%3D5001%26pos%3D42%26display_time%3D1742094369%26pre_seqid%3D17420943694530328354923",
    "hot": 182676,
    "ads": false,
    "readCount": 3116000,
    "discussCount": 283,
    "origin": 49
  },
  {
    "title": "也门遭袭已致13死",
    "category": "社会",
    "description": "总台记者当地时间16日获悉，据胡塞武装控制的卫生部门的最新消息，也门首都萨那遭袭，死亡人数上升至13人，另有9人受伤。",
    "url": "https://m.weibo.cn/search?containerid=100103type%3D1%26t%3D10%26q%3D%23%E4%B9%9F%E9%97%A8%E9%81%AD%E8%A2%AD%E5%B7%B2%E8%87%B413%E6%AD%BB%23&stream_entry_id=31&isnewpage=1&extparam=seat%3D1%26q%3D%2523%25E4%25B9%259F%25E9%2597%25A8%25E9%2581%25AD%25E8%25A2%25AD%25E5%25B7%25B2%25E8%2587%25B413%25E6%25AD%25BB%2523%26dgr%3D0%26filter_type%3Drealtimehot%26c_type%3D31%26realpos%3D44%26band_rank%3D44%26cate%3D5001%26flag%3D0%26stream_entry_id%3D31%26lcate%3D5001%26pos%3D43%26display_time%3D1742094369%26pre_seqid%3D17420943694530328354923",
    "hot": 177808,
    "ads": false,
    "readCount": 6381000,
    "discussCount": 807,
    "origin": 128
  },
  {
    "title": "多家卫生巾品牌发声",
    "category": "财经",
    "description": "3月15日，央视“3·15”晚会曝光位于济宁市梁山县的梁山希希纸制品有限公司（以下简称“希希纸制品”）销售劣质卫生巾、婴儿纸尿裤。多家卫生巾品牌直播间紧急停播，晚些时候陆续发布官方声明。",
    "url": "https://m.weibo.cn/search?containerid=100103type%3D1%26t%3D10%26q%3D%23%E5%A4%9A%E5%AE%B6%E5%8D%AB%E7%94%9F%E5%B7%BE%E5%93%81%E7%89%8C%E5%8F%91%E5%A3%B0%23&stream_entry_id=31&isnewpage=1&extparam=seat%3D1%26q%3D%2523%25E5%25A4%259A%25E5%25AE%25B6%25E5%258D%25AB%25E7%2594%259F%25E5%25B7%25BE%25E5%2593%2581%25E7%2589%258C%25E5%258F%2591%25E5%25A3%25B0%2523%26dgr%3D0%26filter_type%3Drealtimehot%26c_type%3D31%26realpos%3D45%26band_rank%3D45%26cate%3D5001%26flag%3D0%26stream_entry_id%3D31%26lcate%3D5001%26pos%3D44%26display_time%3D1742094369%26pre_seqid%3D17420943694530328354923",
    "hot": 166743,
    "ads": false,
    "readCount": 17699000,
    "discussCount": 1677,
    "origin": 378
  },
  {
    "title": "翻新卫生巾企业负责人被控制",
    "category": "社会",
    "description": "央视3·15晚会曝光梁山希希纸制品有限公司销售劣质卫生巾、婴儿纸尿裤问题后，济宁市委、市政府高度重视，立即成立由市场监管、卫生健康、公安等部门组成的联合调查组，第一时间赶赴现场，依法对涉事企业进行查封，控制了企业负责人。",
    "url": "https://m.weibo.cn/search?containerid=100103type%3D1%26t%3D10%26q%3D%23%E7%BF%BB%E6%96%B0%E5%8D%AB%E7%94%9F%E5%B7%BE%E4%BC%81%E4%B8%9A%E8%B4%9F%E8%B4%A3%E4%BA%BA%E8%A2%AB%E6%8E%A7%E5%88%B6%23&stream_entry_id=31&isnewpage=1&extparam=seat%3D1%26q%3D%2523%25E7%25BF%25BB%25E6%2596%25B0%25E5%258D%25AB%25E7%2594%259F%25E5%25B7%25BE%25E4%25BC%2581%25E4%25B8%259A%25E8%25B4%259F%25E8%25B4%25A3%25E4%25BA%25BA%25E8%25A2%25AB%25E6%258E%25A7%25E5%2588%25B6%2523%26dgr%3D0%26filter_type%3Drealtimehot%26c_type%3D31%26realpos%3D46%26band_rank%3D46%26cate%3D5001%26flag%3D0%26stream_entry_id%3D31%26lcate%3D5001%26pos%3D45%26display_time%3D1742094369%26pre_seqid%3D17420943694530328354923",
    "hot": 161987,
    "ads": false,
    "readCount": 23831000,
    "discussCount": 3147,
    "origin": 405
  },
  {
    "title": "初中生玩打火机30秒烧了整间奶茶店",
    "category": "社会",
    "description": "近日，广东韶关，网友发布视频表示：一名初中生在奶茶店内玩打火机，不慎点燃装饰物，30秒就把奶茶店烧了起来。",
    "url": "https://m.weibo.cn/search?containerid=100103type%3D1%26t%3D10%26q%3D%23%E5%88%9D%E4%B8%AD%E7%94%9F%E7%8E%A9%E6%89%93%E7%81%AB%E6%9C%BA30%E7%A7%92%E7%83%A7%E4%BA%86%E6%95%B4%E9%97%B4%E5%A5%B6%E8%8C%B6%E5%BA%97%23&stream_entry_id=31&isnewpage=1&extparam=seat%3D1%26q%3D%2523%25E5%2588%259D%25E4%25B8%25AD%25E7%2594%259F%25E7%258E%25A9%25E6%2589%2593%25E7%2581%25AB%25E6%259C%25BA30%25E7%25A7%2592%25E7%2583%25A7%25E4%25BA%2586%25E6%2595%25B4%25E9%2597%25B4%25E5%25A5%25B6%25E8%258C%25B6%25E5%25BA%2597%2523%26dgr%3D0%26filter_type%3Drealtimehot%26c_type%3D31%26realpos%3D47%26band_rank%3D47%26cate%3D5001%26flag%3D0%26stream_entry_id%3D31%26lcate%3D5001%26pos%3D46%26display_time%3D1742094369%26pre_seqid%3D17420943694530328354923",
    "hot": 154656,
    "ads": false,
    "readCount": 26027000,
    "discussCount": 1868,
    "origin": 362
  },
  {
    "title": "315奶茶",
    "category": "暂无",
    "url": "https://m.weibo.cn/search?containerid=100103type%3D1%26t%3D10%26q%3D315%E5%A5%B6%E8%8C%B6&stream_entry_id=31&isnewpage=1&extparam=seat%3D1%26q%3D315%25E5%25A5%25B6%25E8%258C%25B6%26dgr%3D0%26filter_type%3Drealtimehot%26c_type%3D31%26realpos%3D48%26band_rank%3D48%26cate%3D5001%26flag%3D0%26stream_entry_id%3D31%26lcate%3D5001%26pos%3D47%26display_time%3D1742094369%26pre_seqid%3D17420943694530328354923",
    "hot": 148321,
    "ads": false,
    "readCount": 120000000,
    "discussCount": 28000,
    "origin": 6808
  },
  {
    "title": "冰湖重生",
    "category": "电视剧",
    "description": "剧集冰湖重生目前拍摄中，敬请期待",
    "url": "https://m.weibo.cn/search?containerid=100103type%3D1%26t%3D10%26q%3D%E5%86%B0%E6%B9%96%E9%87%8D%E7%94%9F&stream_entry_id=31&isnewpage=1&extparam=seat%3D1%26q%3D%25E5%2586%25B0%25E6%25B9%2596%25E9%2587%258D%25E7%2594%259F%26dgr%3D0%26filter_type%3Drealtimehot%26c_type%3D31%26realpos%3D49%26band_rank%3D49%26cate%3D5001%26flag%3D1%26stream_entry_id%3D31%26lcate%3D5001%26pos%3D48%26display_time%3D1742094369%26pre_seqid%3D17420943694530328354923",
    "hot": 146574,
    "ads": false,
    "readCount": 43142000,
    "discussCount": 146000,
    "origin": 5451
  },
  {
    "title": "与辉同行回应带货虾仁被质疑",
    "category": "财经",
    "description": "央视315晚会曝光增重虾仁的问题，有网友反映“与辉同行”直播间曾带货的一款“大岸浪花大号虾仁”生产商为此次被点名的生产企业之一——湛江良基冷冻食品有限公司。对此，与辉同行方面回应称，已经关注到相关情况，很重视，目前正在核实情况，也正在密切关注该事情的进展，有结论后会尽快反馈。",
    "url": "https://m.weibo.cn/search?containerid=100103type%3D1%26t%3D10%26q%3D%23%E4%B8%8E%E8%BE%89%E5%90%8C%E8%A1%8C%E5%9B%9E%E5%BA%94%E5%B8%A6%E8%B4%A7%E8%99%BE%E4%BB%81%E8%A2%AB%E8%B4%A8%E7%96%91%23&stream_entry_id=31&isnewpage=1&extparam=seat%3D1%26q%3D%2523%25E4%25B8%258E%25E8%25BE%2589%25E5%2590%258C%25E8%25A1%258C%25E5%259B%259E%25E5%25BA%2594%25E5%25B8%25A6%25E8%25B4%25A7%25E8%2599%25BE%25E4%25BB%2581%25E8%25A2%25AB%25E8%25B4%25A8%25E7%2596%2591%2523%26dgr%3D0%26filter_type%3Drealtimehot%26c_type%3D31%26realpos%3D50%26band_rank%3D50%26cate%3D5001%26flag%3D1%26stream_entry_id%3D31%26lcate%3D5001%26pos%3D49%26display_time%3D1742094369%26pre_seqid%3D17420943694530328354923",
    "hot": 146542,
    "ads": false,
    "readCount": 3528000,
    "discussCount": 193,
    "origin": 47
  },
  {
    "title": "稳步扩大制度型开放",
    "category": "财经-宏观经济",
    "description": "近日，国务院印发文件，推动在有条件的自由贸易试验区和自由贸易港试点对接国际高标准推进制度型开放，我国在稳步扩大制度型开放上又迈出重要一步。在新形势下稳步扩大制度型开放，既是构建开放型世界经济的客观要求，也是推动经济高质量发展的必然选择。",
    "url": "https://m.weibo.cn/search?containerid=100103type%3D1%26t%3D10%26q%3D%23%E7%A8%B3%E6%AD%A5%E6%89%A9%E5%A4%A7%E5%88%B6%E5%BA%A6%E5%9E%8B%E5%BC%80%E6%94%BE%23&stream_entry_id=51&isnewpage=1&extparam=seat%3D1%26q%3D%2523%25E7%25A8%25B3%25E6%25AD%25A5%25E6%2589%25A9%25E5%25A4%25A7%25E5%2588%25B6%25E5%25BA%25A6%25E5%259E%258B%25E5%25BC%2580%25E6%2594%25BE%2523%26cate%3D10103%26pos%3D0%26filter_type%3Drealtimehot%26stream_entry_id%3D51%26c_type%3D51%26dgr%3D0%26display_time%3D1742094369%26pre_seqid%3D17420943694530328354923",
    "hot": 0,
    "ads": false,
    "readCount": 24977000,
    "discussCount": 650,
    "origin": 65
  }
]